mindleap_starter_python_client/__init__.py
mindleap_starter_python_client/data_types.py
mindleap_starter_python_client/environment.py
mindleap_starter_python_client/exploration.py
mindleap_starter_python_client/exploration_service.py
mindleap_starter_python_client/graph_model.py
mindleap_starter_python_client/graph_model_service.py
mindleap_starter_python_client/services.py
mindleap_starter_python_client-1.0.6.dist-info/licenses/LICENSE
mindleap_starter_python_client-1.0.6.dist-info/METADATA
mindleap_starter_python_client-1.0.6.dist-info/WHEEL
mindleap_starter_python_client-1.0.6.dist-info/top_level.txt
mindleap_starter_python_client-1.0.6.dist-info/RECORD
