Metadata-Version: 2.4
Name: mindleap-starter-python-client
Version: 1.0.6
Summary: The official Python client library for Mindleap Starter
Author: Erik Mata
License-Expression: MIT
Project-URL: Homepage, https://mindleap-io.github.io/python-client-starter/
Project-URL: Issues, https://github.com/mindleap-io/python-client-starter/issues
Classifier: Programming Language :: Python :: 3
Classifier: Operating System :: OS Independent
Requires-Python: >=3.13
License-File: LICENSE
Dynamic: license-file
